{
  "disclaimer": "Usage subject to terms: https://openexchangerates.org/terms",
  "license": "https://openexchangerates.org/license",
  "timestamp": 1693821600,
  "base": "USD",
  "rates": {
    "AED": 3.673075,
    "AFN": 73.840074,
    "ALL": 100.52234,
    "AMD": 388.17327,
    "ANG": 1.813577,
    "AOA": 825.001,
    "ARS": 349.903705,
    "AUD": 1.546695,
    "AWG": 1.8,
    "AZN": 1.7,
    "BAM": 1.814479,
    "BBD": 2,
    "BDT": 109.937487,
    "BGN": 1.8118,
    "BHD": 0.377049,
    "BIF": 2848.337987,
    "BMD": 1,
    "BND": 1.358711,
    "BOB": 6.953529,
    "BRL": 4.9481,
    "BSD": 1,
    "BTC": 0.000038550226,
    "BTN": 83.266724,
    "BWP": 13.589765,
    "BYN": 2.540033,
    "BZD": 2.028352,
    "CAD": 1.359935,
    "CDF": 2496.595554,
    "CHF": 0.884233,
    "CLF": 0.030944,
    "CLP": 854.700855,
    "CNH": 7.272862,
    "CNY": 7.2708,
    "COP": 4108.395123,
    "CRC": 542.556963,
    "CUC": 1,
    "CUP": 25.75,
    "CVE": 102.298972,
    "CZK": 22.348601,
    "DJF": 179.1681,
    "DKK": 6.904033,
    "DOP": 57.122181,
    "DZD": 136.698773,
    "EGP": 30.9505,
    "ERN": 15,
    "ETB": 55.603535,
    "EUR": 0.926356,
    "FJD": 2.25945,
    "FKP": 0.791757,
    "GBP": 0.791757,
    "GEL": 2.628645,
    "GGP": 0.791757,
    "GHS": 11.502315,
    "GIP": 0.791757,
    "GMD": 60.8134,
    "GNF": 8641.213528,
    "GTQ": 7.919323,
    "GYD": 210.535531,
    "HKD": 7.83389,
    "HNL": 24.779541,
    "HRK": 6.979122,
    "HTG": 136.455584,
    "HUF": 354.472044,
    "IDR": 15213.401616,
    "ILS": 3.81484,
    "IMP": 0.791757,
    "INR": 82.752,
    "IQD": 1317.869267,
    "IRR": 42250,
    "ISK": 132.38,
    "JEP": 0.791757,
    "JMD": 155.250607,
    "JOD": 0.7081,
    "JPY": 146.3925625,
    "KES": 145.75,
    "KGS": 88.2581,
    "KHR": 4185.125989,
    "KMF": 455.704244,
    "KPW": 900,
    "KRW": 1319.712652,
    "KWD": 0.308386,
    "KYD": 0.838594,
    "KZT": 460.451969,
    "LAK": 19808.049439,
    "LBP": 15124.3985,
    "LKR": 322.013137,
    "LRD": 185.997,
    "LSL": 18.845228,
    "LYD": 4.846596,
    "MAD": 10.285378,
    "MDL": 17.942034,
    "MGA": 4542.302859,
    "MKD": 57.083436,
    "MMK": 2113.243492,
    "MNT": 3450,
    "MOP": 8.131648,
    "MRU": 38.223533,
    "MUR": 46.62,
    "MVR": 15.399601,
    "MWK": 1075.732724,
    "MXN": 17.101763,
    "MYR": 4.655,
    "MZN": 63.830001,
    "NAD": 18.905025,
    "NGN": 780.333289,
    "NIO": 36.822965,
    "NOK": 10.6509,
    "NPR": 133.22729,
    "NZD": 1.681741,
    "OMR": 0.385016,
    "PAB": 1,
    "PEN": 3.716352,
    "PGK": 3.683224,
    "PHP": 56.583251,
    "PKR": 308.162187,
    "PLN": 4.136796,
    "PYG": 7323.703513,
    "QAR": 3.66881,
    "RON": 4.5826,
    "RSD": 108.634967,
    "RUB": 96.602502,
    "RWF": 1197.456209,
    "SAR": 3.751152,
    "SBD": 8.36952,
    "SCR": 13.3111,
    "SDG": 601.5,
    "SEK": 11.015811,
    "SGD": 1.354273,
    "SHP": 0.791757,
    "SLL": 20969.5,
    "SOS": 573.073924,
    "SRD": 38.2005,
    "SSP": 130.26,
    "STD": 22281.8,
    "STN": 22.730225,
    "SVC": 8.805288,
    "SYP": 2512.53,
    "SZL": 18.835295,
    "THB": 35.22,
    "TJS": 11.054116,
    "TMT": 3.50333,
    "TND": 3.0935,
    "TOP": 2.383987,
    "TRY": 26.777501,
    "TTD": 6.837527,
    "TWD": 31.8905,
    "TZS": 2520.72965,
    "UAH": 37.164779,
    "UGX": 3742.563315,
    "USD": 1,
    "UYU": 37.607754,
    "UZS": 12177.526654,
    "VES": 32.667797,
    "VND": 24085,
    "VUV": 118.722,
    "WST": 2.7185,
    "XAF": 607.649501,
    "XAG": 0.04148775,
    "XAU": 0.00051519,
    "XCD": 2.70255,
    "XDR": 0.75844,
    "XOF": 607.649501,
    "XPD": 0.00081412,
    "XPF": 110.543639,
    "XPT": 0.00103954,
    "YER": 250.247994,
    "ZAR": 18.904284,
    "ZMW": 20.352176,
    "ZWL": 322
  }
}