{
  "disclaimer": "Usage subject to terms: https://openexchangerates.org/terms",
  "license": "https://openexchangerates.org/license",
  "timestamp": 1677484800,
  "base": "USD",
  "rates": {
    "AED": 3.67286,
    "AFN": 89.067561,
    "ALL": 109.002403,
    "AMD": 393.452338,
    "ANG": 1.805707,
    "AOA": 506.5,
    "ARS": 195.7045,
    "AUD": 1.489053,
    "AWG": 1.8,
    "AZN": 1.7,
    "BAM": 1.852252,
    "BBD": 2,
    "BDT": 107.274892,
    "BGN": 1.85494,
    "BHD": 0.376976,
    "BIF": 2081.526546,
    "BMD": 1,
    "BND": 1.348631,
    "BOB": 6.923252,
    "BRL": 5.210601,
    "BSD": 1,
    "BTC": 0.000042675707,
    "BTN": 82.912568,
    "BWP": 13.340941,
    "BYN": 2.528837,
    "BZD": 2.019528,
    "CAD": 1.360193,
    "CDF": 2083.97157,
    "CHF": 0.941678,
    "CLF": 0.029481,
    "CLP": 813.47248,
    "CNH": 6.980976,
    "CNY": 6.9646,
    "COP": 4872.448807,
    "CRC": 562.319913,
    "CUC": 1,
    "CUP": 25.75,
    "CVE": 104.42554,
    "CZK": 22.423999,
    "DJF": 178.390825,
    "DKK": 7.05688,
    "DOP": 55.891018,
    "DZD": 137.066372,
    "EGP": 30.6784,
    "ERN": 15,
    "ETB": 53.886334,
    "EUR": 0.948038,
    "FJD": 2.2208,
    "FKP": 0.836439,
    "GBP": 0.836439,
    "GEL": 2.635,
    "GGP": 0.836439,
    "GHS": 12.899652,
    "GIP": 0.836439,
    "GMD": 61.1,
    "GNF": 8623.350203,
    "GTQ": 7.825004,
    "GYD": 211.408056,
    "HKD": 7.846075,
    "HNL": 24.701449,
    "HRK": 7.143021,
    "HTG": 150.10279,
    "HUF": 361.10005,
    "IDR": 15273.980917,
    "ILS": 3.684207,
    "IMP": 0.836439,
    "INR": 82.892746,
    "IQD": 1462.286277,
    "IRR": 42325,
    "ISK": 144.77,
    "JEP": 0.836439,
    "JMD": 154.560019,
    "JOD": 0.7101,
    "JPY": 136.18496,
    "KES": 126.7,
    "KGS": 87.42,
    "KHR": 4053.593774,
    "KMF": 466.900353,
    "KPW": 900,
    "KRW": 1322.041546,
    "KWD": 0.30731,
    "KYD": 0.834896,
    "KZT": 449.949675,
    "LAK": 16895.576975,
    "LBP": 15038.633157,
    "LKR": 365.691466,
    "LRD": 153.775887,
    "LSL": 18.449912,
    "LYD": 4.831524,
    "MAD": 10.433556,
    "MDL": 18.905468,
    "MGA": 4310.296911,
    "MKD": 58.473232,
    "MMK": 2103.98164,
    "MNT": 3406.965265,
    "MOP": 8.099403,
    "MRU": 36.419081,
    "MUR": 46.150001,
    "MVR": 15.35,
    "MWK": 1028.387967,
    "MXN": 18.379968,
    "MYR": 4.4785,
    "MZN": 63.899991,
    "NAD": 18.41,
    "NGN": 460.882058,
    "NIO": 36.608394,
    "NOK": 10.381317,
    "NPR": 132.657481,
    "NZD": 1.625962,
    "OMR": 0.38502,
    "PAB": 1,
    "PEN": 3.811557,
    "PGK": 3.531735,
    "PHP": 55.569497,
    "PKR": 258.441148,
    "PLN": 4.476498,
    "PYG": 7327.010913,
    "QAR": 3.656811,
    "RON": 4.664,
    "RSD": 111.2,
    "RUB": 75.644326,
    "RWF": 1091.172049,
    "SAR": 3.752063,
    "SBD": 8.245284,
    "SCR": 12.924325,
    "SDG": 588,
    "SEK": 10.510847,
    "SGD": 1.350317,
    "SHP": 0.836439,
    "SLL": 17665,
    "SOS": 569.544976,
    "SRD": 33.661,
    "SSP": 130.26,
    "STD": 22823.990504,
    "STN": 23.202076,
    "SVC": 8.76697,
    "SYP": 2512.53,
    "SZL": 18.450087,
    "THB": 35.1315,
    "TJS": 10.013467,
    "TMT": 3.510001,
    "TND": 3.13,
    "TOP": 2.361752,
    "TRY": 18.8874,
    "TTD": 6.800481,
    "TWD": 30.701499,
    "TZS": 2339,
    "UAH": 36.821381,
    "UGX": 3727.092464,
    "USD": 1,
    "UYU": 38.88665,
    "UZS": 11371.976622,
    "VES": 24.38578,
    "VND": 23803.86162,
    "VUV": 118.044,
    "WST": 2.69755,
    "XAF": 621.871954,
    "XAG": 0.048391,
    "XAU": 0.00055226,
    "XCD": 2.70255,
    "XDR": 0.752986,
    "XOF": 621.871954,
    "XPD": 0.00070747,
    "XPF": 113.130988,
    "XPT": 0.00109325,
    "YER": 250.350023,
    "ZAR": 18.396198,
    "ZMW": 19.762392,
    "ZWL": 322
  }
}