{
  "disclaimer": "Usage subject to terms: https://openexchangerates.org/terms",
  "license": "https://openexchangerates.org/license",
  "timestamp": 1682665200,
  "base": "USD",
  "rates": {
    "AED": 3.67198,
    "AFN": 86.411977,
    "ALL": 100.592232,
    "AMD": 388.20333,
    "ANG": 1.803929,
    "AOA": 508.802333,
    "ARS": 222.009,
    "AUD": 1.514314,
    "AWG": 1.8025,
    "AZN": 1.7,
    "BAM": 1.770724,
    "BBD": 2,
    "BDT": 106.145672,
    "BGN": 1.775113,
    "BHD": 0.377049,
    "BIF": 2084.678211,
    "BMD": 1,
    "BND": 1.337007,
    "BOB": 6.909539,
    "BRL": 4.9782,
    "BSD": 1,
    "BTC": 0.00003392075,
    "BTN": 81.759257,
    "BWP": 13.187908,
    "BYN": 2.526474,
    "BZD": 2.017572,
    "CAD": 1.362419,
    "CDF": 2232.148362,
    "CHF": 0.893868,
    "CLF": 0.029102,
    "CLP": 803.36,
    "CNH": 6.930435,
    "CNY": 6.9173,
    "COP": 4647.930758,
    "CRC": 534.517612,
    "CUC": 1,
    "CUP": 25.75,
    "CVE": 100.045715,
    "CZK": 21.300057,
    "DJF": 178.213753,
    "DKK": 6.76094,
    "DOP": 54.693341,
    "DZD": 135.437905,
    "EGP": 30.904,
    "ERN": 15,
    "ETB": 54.579062,
    "EUR": 0.907024,
    "FJD": 2.22225,
    "FKP": 0.801375,
    "GBP": 0.801375,
    "GEL": 2.505,
    "GGP": 0.801375,
    "GHS": 11.874523,
    "GIP": 0.801375,
    "GMD": 61.13,
    "GNF": 8604.039615,
    "GTQ": 7.804012,
    "GYD": 211.486938,
    "HKD": 7.849915,
    "HNL": 24.600676,
    "HRK": 6.833304,
    "HTG": 154.644323,
    "HUF": 338.178156,
    "IDR": 14667.991937,
    "ILS": 3.63999,
    "IMP": 0.801375,
    "INR": 81.78785,
    "IQD": 1460,
    "IRR": 42275,
    "ISK": 135.23,
    "JEP": 0.801375,
    "JMD": 153.277324,
    "JOD": 0.7094,
    "JPY": 135.63775,
    "KES": 136,
    "KGS": 87.52,
    "KHR": 4109.881063,
    "KMF": 446.749564,
    "KPW": 900,
    "KRW": 1339.681762,
    "KWD": 0.306331,
    "KYD": 0.833273,
    "KZT": 456.180019,
    "LAK": 17287.478003,
    "LBP": 15024.081639,
    "LKR": 322.013115,
    "LRD": 164.400042,
    "LSL": 18.295142,
    "LYD": 4.767773,
    "MAD": 10.092263,
    "MDL": 17.950182,
    "MGA": 4420.742904,
    "MKD": 55.886629,
    "MMK": 2102.000618,
    "MNT": 3519,
    "MOP": 8.085029,
    "MRU": 34.342757,
    "MUR": 44.95,
    "MVR": 15.35,
    "MWK": 1027.335886,
    "MXN": 18.082115,
    "MYR": 4.462,
    "MZN": 63.899991,
    "NAD": 18.3,
    "NGN": 460.47,
    "NIO": 36.612942,
    "NOK": 10.64559,
    "NPR": 130.94836,
    "NZD": 1.629315,
    "OMR": 0.385022,
    "PAB": 1,
    "PEN": 3.728516,
    "PGK": 3.527135,
    "PHP": 55.530499,
    "PKR": 284.134713,
    "PLN": 4.157049,
    "PYG": 7276.427055,
    "QAR": 3.647196,
    "RON": 4.4761,
    "RSD": 106.360247,
    "RUB": 81.499593,
    "RWF": 1112.173305,
    "SAR": 3.750901,
    "SBD": 8.334636,
    "SCR": 13.185578,
    "SDG": 599.5,
    "SEK": 10.290982,
    "SGD": 1.336462,
    "SHP": 0.801375,
    "SLL": 17665,
    "SOS": 569.046738,
    "SRD": 37.3,
    "SSP": 130.26,
    "STD": 22823.990504,
    "STN": 22.203191,
    "SVC": 8.749502,
    "SYP": 2512.53,
    "SZL": 18.281504,
    "THB": 34.164615,
    "TJS": 10.929148,
    "TMT": 3.51,
    "TND": 3.04,
    "TOP": 2.363414,
    "TRY": 19.455575,
    "TTD": 6.795466,
    "TWD": 30.750498,
    "TZS": 2350,
    "UAH": 36.964025,
    "UGX": 3759.081172,
    "USD": 1,
    "UYU": 38.728685,
    "UZS": 11389.592128,
    "VES": 24.699487,
    "VND": 23460.413462,
    "VUV": 118.979,
    "WST": 2.72551,
    "XAF": 594.968509,
    "XAG": 0.04007309,
    "XAU": 0.00050356,
    "XCD": 2.70255,
    "XDR": 0.741684,
    "XOF": 594.968509,
    "XPD": 0.00066388,
    "XPF": 108.236712,
    "XPT": 0.00092779,
    "YER": 250.399984,
    "ZAR": 18.356431,
    "ZMW": 17.781745,
    "ZWL": 322
  }
}