{
  "disclaimer": "Usage subject to terms: https://openexchangerates.org/terms",
  "license": "https://openexchangerates.org/license",
  "timestamp": 1668524400,
  "base": "USD",
  "rates": {
    "AED": 3.673,
    "AFN": 88.539715,
    "ALL": 112.441596,
    "AMD": 395.746694,
    "ANG": 1.803373,
    "AOA": 497.1475,
    "ARS": 162.107039,
    "AUD": 1.486724,
    "AWG": 1.8,
    "AZN": 1.7,
    "BAM": 1.87963,
    "BBD": 2,
    "BDT": 102.61209,
    "BGN": 1.880481,
    "BHD": 0.376872,
    "BIF": 2070.144749,
    "BMD": 1,
    "BND": 1.369756,
    "BOB": 6.914062,
    "BRL": 5.332,
    "BSD": 1,
    "BTC": 0.000059112852,
    "BTN": 81.014649,
    "BWP": 12.894623,
    "BYN": 2.526669,
    "BZD": 2.016866,
    "CAD": 1.331427,
    "CDF": 2055.715777,
    "CHF": 0.943818,
    "CLF": 0.032374,
    "CLP": 893.53,
    "CNH": 7.044412,
    "CNY": 7.0447,
    "COP": 4812.49,
    "CRC": 609.729963,
    "CUC": 1,
    "CUP": 25.75,
    "CVE": 107.875,
    "CZK": 23.384,
    "DJF": 178.136565,
    "DKK": 7.152007,
    "DOP": 54.253038,
    "DZD": 138.423751,
    "EGP": 24.46362,
    "ERN": 15,
    "ETB": 53.434783,
    "EUR": 0.961492,
    "FJD": 2.22425,
    "FKP": 0.838678,
    "GBP": 0.838678,
    "GEL": 2.7,
    "GGP": 0.838678,
    "GHS": 14.508421,
    "GIP": 0.838678,
    "GMD": 61.35,
    "GNF": 8617.611382,
    "GTQ": 7.809528,
    "GYD": 209.338144,
    "HKD": 7.825676,
    "HNL": 24.715776,
    "HRK": 7.2539,
    "HTG": 136.082855,
    "HUF": 390.94,
    "IDR": 15543.99443,
    "ILS": 3.416485,
    "IMP": 0.838678,
    "INR": 80.900794,
    "IQD": 1460.401174,
    "IRR": 42400,
    "ISK": 143.55,
    "JEP": 0.838678,
    "JMD": 153.812866,
    "JOD": 0.7099,
    "JPY": 139.14725,
    "KES": 122.08,
    "KGS": 84.073223,
    "KHR": 4135.993411,
    "KMF": 479.849852,
    "KPW": 900,
    "KRW": 1311.989193,
    "KWD": 0.307701,
    "KYD": 0.833886,
    "KZT": 459.929854,
    "LAK": 17304.667766,
    "LBP": 1513.145831,
    "LKR": 367.722544,
    "LRD": 153.800017,
    "LSL": 17.212501,
    "LYD": 4.967338,
    "MAD": 10.670222,
    "MDL": 19.131518,
    "MGA": 4322.518745,
    "MKD": 59.714872,
    "MMK": 2101.272757,
    "MNT": 3406.965265,
    "MOP": 8.064485,
    "MRU": 38.003345,
    "MUR": 43.794919,
    "MVR": 15.41,
    "MWK": 1027.066817,
    "MXN": 19.354576,
    "MYR": 4.5545,
    "MZN": 63.899991,
    "NAD": 17.3,
    "NGN": 441.69,
    "NIO": 36.016873,
    "NOK": 9.951479,
    "NPR": 129.623765,
    "NZD": 1.628586,
    "OMR": 0.38445,
    "PAB": 1,
    "PEN": 3.852234,
    "PGK": 3.525732,
    "PHP": 57.279998,
    "PKR": 221.984422,
    "PLN": 4.5228,
    "PYG": 7047.703261,
    "QAR": 3.658258,
    "RON": 4.719,
    "RSD": 112.722248,
    "RUB": 60.378504,
    "RWF": 1070.279739,
    "SAR": 3.75771,
    "SBD": 8.223823,
    "SCR": 12.871806,
    "SDG": 569.5,
    "SEK": 10.38897,
    "SGD": 1.36934,
    "SHP": 0.838678,
    "SLL": 17665,
    "SOS": 568.833458,
    "SRD": 30.3825,
    "SSP": 130.26,
    "STD": 22823.990504,
    "STN": 24.25,
    "SVC": 8.75603,
    "SYP": 2512.53,
    "SZL": 17.212502,
    "THB": 35.527,
    "TJS": 10.071116,
    "TMT": 3.5,
    "TND": 3.21375,
    "TOP": 2.371842,
    "TRY": 18.613505,
    "TTD": 6.788074,
    "TWD": 31.046,
    "TZS": 2333.41,
    "UAH": 36.953821,
    "UGX": 3757.148084,
    "USD": 1,
    "UYU": 40.019218,
    "UZS": 11177.277902,
    "VES": 9.28135,
    "VND": 24773.941239,
    "VUV": 122.25878,
    "WST": 2.793855,
    "XAF": 630.69728,
    "XAG": 0.04595597,
    "XAU": 0.00056418,
    "XCD": 2.70255,
    "XDR": 0.743991,
    "XOF": 630.69728,
    "XPD": 0.00048286,
    "XPF": 114.736492,
    "XPT": 0.00097994,
    "YER": 250.249937,
    "ZAR": 17.275261,
    "ZMW": 16.494631,
    "ZWL": 322
  }
}