{
  "disclaimer": "Usage subject to terms: https://openexchangerates.org/terms",
  "license": "https://openexchangerates.org/license",
  "timestamp": 1694505600,
  "base": "USD",
  "rates": {
    "AED": 3.67306,
    "AFN": 78.034252,
    "ALL": 99.591408,
    "AMD": 384.774887,
    "ANG": 1.800277,
    "AOA": 826.708667,
    "ARS": 349.9734,
    "AUD": 1.555595,
    "AWG": 1.8025,
    "AZN": 1.7,
    "BAM": 1.820365,
    "BBD": 2,
    "BDT": 109.633272,
    "BGN": 1.82205,
    "BHD": 0.376996,
    "BIF": 2829.04363,
    "BMD": 1,
    "BND": 1.3596,
    "BOB": 6.902489,
    "BRL": 4.9309,
    "BSD": 1,
    "BTC": 0.000038729764,
    "BTN": 82.849611,
    "BWP": 13.609583,
    "BYN": 2.521314,
    "BZD": 2.013496,
    "CAD": 1.358353,
    "CDF": 2479.239561,
    "CHF": 0.890976,
    "CLF": 0.032136,
    "CLP": 891.75,
    "CNH": 7.309765,
    "CNY": 7.2956,
    "COP": 4021.69251,
    "CRC": 535.927662,
    "CUC": 1,
    "CUP": 25.75,
    "CVE": 102.629871,
    "CZK": 22.996436,
    "DJF": 177.857429,
    "DKK": 6.961843,
    "DOP": 56.738649,
    "DZD": 137.111,
    "EGP": 30.8986,
    "ERN": 15,
    "ETB": 55.220403,
    "EUR": 0.933382,
    "FJD": 2.26715,
    "FKP": 0.80095,
    "GBP": 0.80095,
    "GEL": 2.615,
    "GGP": 0.80095,
    "GHS": 11.462265,
    "GIP": 0.80095,
    "GMD": 60.5,
    "GNF": 8575.32049,
    "GTQ": 7.866753,
    "GYD": 209.150251,
    "HKD": 7.830256,
    "HNL": 24.607223,
    "HRK": 7.03094,
    "HTG": 134.861664,
    "HUF": 360.861734,
    "IDR": 15354.918231,
    "ILS": 3.810824,
    "IMP": 0.80095,
    "INR": 82.988652,
    "IQD": 1308.171101,
    "IRR": 42265,
    "ISK": 134.13,
    "JEP": 0.80095,
    "JMD": 154.188369,
    "JOD": 0.7081,
    "JPY": 146.81125,
    "KES": 146.45,
    "KGS": 88.39,
    "KHR": 4129.897483,
    "KMF": 458.250216,
    "KPW": 900,
    "KRW": 1327.254956,
    "KWD": 0.308591,
    "KYD": 0.832465,
    "KZT": 462.257788,
    "LAK": 19814.195694,
    "LBP": 15013.784493,
    "LKR": 322.654575,
    "LRD": 186.350012,
    "LSL": 18.904785,
    "LYD": 4.850194,
    "MAD": 10.183592,
    "MDL": 17.974387,
    "MGA": 4510.468568,
    "MKD": 57.410975,
    "MMK": 2097.752945,
    "MNT": 3450,
    "MOP": 8.059568,
    "MRU": 38.312547,
    "MUR": 45.131872,
    "MVR": 15.46,
    "MWK": 1098.019631,
    "MXN": 17.290795,
    "MYR": 4.6775,
    "MZN": 63.92499,
    "NAD": 18.995,
    "NGN": 749.719896,
    "NIO": 36.551993,
    "NOK": 10.675505,
    "NPR": 132.558605,
    "NZD": 1.692621,
    "OMR": 0.384986,
    "PAB": 1,
    "PEN": 3.71491,
    "PGK": 3.655994,
    "PHP": 56.658995,
    "PKR": 297.22746,
    "PLN": 4.373642,
    "PYG": 7255.220444,
    "QAR": 3.641,
    "RON": 4.6329,
    "RSD": 109.386,
    "RUB": 94.883414,
    "RWF": 1202.996488,
    "SAR": 3.750892,
    "SBD": 8.404364,
    "SCR": 12.802497,
    "SDG": 601.5,
    "SEK": 11.092109,
    "SGD": 1.36228,
    "SHP": 0.80095,
    "SLL": 20969.5,
    "SOS": 569.899803,
    "SRD": 38.4695,
    "SSP": 130.26,
    "STD": 22281.8,
    "STN": 22.803425,
    "SVC": 8.740693,
    "SYP": 2512.53,
    "SZL": 18.900958,
    "THB": 35.622001,
    "TJS": 10.988044,
    "TMT": 3.5,
    "TND": 3.117,
    "TOP": 2.391682,
    "TRY": 26.893199,
    "TTD": 6.778667,
    "TWD": 32.046599,
    "TZS": 2502.234,
    "UAH": 36.88549,
    "UGX": 3716.5023,
    "USD": 1,
    "UYU": 38.138154,
    "UZS": 12150.029094,
    "VES": 33.29845,
    "VND": 24102.1947,
    "VUV": 118.722,
    "WST": 2.7185,
    "XAF": 612.258722,
    "XAG": 0.04341013,
    "XAU": 0.00052109,
    "XCD": 2.70255,
    "XDR": 0.756802,
    "XOF": 612.258722,
    "XPD": 0.00082389,
    "XPF": 111.382149,
    "XPT": 0.00111048,
    "YER": 250.349938,
    "ZAR": 18.917306,
    "ZMW": 20.901899,
    "ZWL": 322
  }
}