{
  "disclaimer": "Usage subject to terms: https://openexchangerates.org/terms",
  "license": "https://openexchangerates.org/license",
  "timestamp": 1677124800,
  "base": "USD",
  "rates": {
    "AED": 3.67296,
    "AFN": 89.305304,
    "ALL": 108.553503,
    "AMD": 392.04293,
    "ANG": 1.803929,
    "AOA": 503.8306,
    "ARS": 194.962356,
    "AUD": 1.463432,
    "AWG": 1.8025,
    "AZN": 1.7,
    "BAM": 1.841691,
    "BBD": 2,
    "BDT": 107.215335,
    "BGN": 1.842205,
    "BHD": 0.376998,
    "BIF": 2079.465694,
    "BMD": 1,
    "BND": 1.341086,
    "BOB": 6.916453,
    "BRL": 5.1525,
    "BSD": 1,
    "BTC": 0.00004091109,
    "BTN": 82.867101,
    "BWP": 13.240141,
    "BYN": 2.526437,
    "BZD": 2.017571,
    "CAD": 1.352252,
    "CDF": 2081.994696,
    "CHF": 0.92931,
    "CLF": 0.02903,
    "CLP": 800,
    "CNH": 6.888328,
    "CNY": 6.8825,
    "COP": 4964.70369,
    "CRC": 558.457724,
    "CUC": 1,
    "CUP": 25.75,
    "CVE": 103.830106,
    "CZK": 22.290401,
    "DJF": 178.21594,
    "DKK": 7.00825,
    "DOP": 56.048248,
    "DZD": 136.980911,
    "EGP": 30.630919,
    "ERN": 15,
    "ETB": 53.821141,
    "EUR": 0.941395,
    "FJD": 2.2008,
    "FKP": 0.828901,
    "GBP": 0.828901,
    "GEL": 2.635,
    "GGP": 0.828901,
    "GHS": 12.862073,
    "GIP": 0.828901,
    "GMD": 61.1,
    "GNF": 8613.652487,
    "GTQ": 7.824855,
    "GYD": 211.200838,
    "HKD": 7.84425,
    "HNL": 24.677953,
    "HRK": 7.092828,
    "HTG": 149.418998,
    "HUF": 358.788428,
    "IDR": 15183.870925,
    "ILS": 3.631595,
    "IMP": 0.828901,
    "INR": 82.779502,
    "IQD": 1460.911495,
    "IRR": 42350,
    "ISK": 143.93,
    "JEP": 0.828901,
    "JMD": 154.396562,
    "JOD": 0.7094,
    "JPY": 134.768,
    "KES": 126.22,
    "KGS": 87.42,
    "KHR": 4064.141841,
    "KMF": 462.849915,
    "KPW": 900,
    "KRW": 1294.878149,
    "KWD": 0.30666,
    "KYD": 0.834134,
    "KZT": 449.790254,
    "LAK": 16875.057913,
    "LBP": 15024.144735,
    "LKR": 365.343857,
    "LRD": 157.799982,
    "LSL": 18.284696,
    "LYD": 4.819911,
    "MAD": 10.406648,
    "MDL": 18.812678,
    "MGA": 4284.548987,
    "MKD": 58.019259,
    "MMK": 2102.063453,
    "MNT": 3406.965265,
    "MOP": 8.089173,
    "MRU": 36.364835,
    "MUR": 45.550818,
    "MVR": 15.35,
    "MWK": 1027.41309,
    "MXN": 18.3447,
    "MYR": 4.434,
    "MZN": 64.000005,
    "NAD": 18.27,
    "NGN": 460.434285,
    "NIO": 36.574307,
    "NOK": 10.320878,
    "NPR": 132.588797,
    "NZD": 1.601037,
    "OMR": 0.385041,
    "PAB": 1,
    "PEN": 3.838791,
    "PGK": 3.52692,
    "PHP": 54.978505,
    "PKR": 261.99879,
    "PLN": 4.470796,
    "PYG": 7329.391634,
    "QAR": 3.653382,
    "RON": 4.6279,
    "RSD": 110.433254,
    "RUB": 74.906367,
    "RWF": 1102.687411,
    "SAR": 3.751454,
    "SBD": 8.266721,
    "SCR": 13.140974,
    "SDG": 587.5,
    "SEK": 10.389659,
    "SGD": 1.33821,
    "SHP": 0.828901,
    "SLL": 17665,
    "SOS": 569.04165,
    "SRD": 33.313,
    "SSP": 130.26,
    "STD": 22823.990504,
    "STN": 23.070223,
    "SVC": 8.757557,
    "SYP": 2512.53,
    "SZL": 18.282891,
    "THB": 34.5845,
    "TJS": 10.704548,
    "TMT": 3.51,
    "TND": 3.1525,
    "TOP": 2.342338,
    "TRY": 18.8805,
    "TTD": 6.792282,
    "TWD": 30.328301,
    "TZS": 2341.22231,
    "UAH": 36.786415,
    "UGX": 3712.510923,
    "USD": 1,
    "UYU": 39.314396,
    "UZS": 11327.618813,
    "VES": 24.370898,
    "VND": 23849.278023,
    "VUV": 118.044,
    "WST": 2.69755,
    "XAF": 617.514663,
    "XAG": 0.04621724,
    "XAU": 0.00054714,
    "XCD": 2.70255,
    "XDR": 0.750311,
    "XOF": 617.514663,
    "XPD": 0.00066801,
    "XPF": 112.33831,
    "XPT": 0.00104868,
    "YER": 250.350023,
    "ZAR": 18.2041,
    "ZMW": 19.613454,
    "ZWL": 322
  }
}