{
  "disclaimer": "Usage subject to terms: https://openexchangerates.org/terms",
  "license": "https://openexchangerates.org/license",
  "timestamp": 1664827200,
  "base": "USD",
  "rates": {
    "AED": 3.67303,
    "AFN": 88.500008,
    "ALL": 118.95,
    "AMD": 403.78045,
    "ANG": 1.801732,
    "AOA": 434.11015,
    "ARS": 148.229652,
    "AUD": 1.535044,
    "AWG": 1.8025,
    "AZN": 1.7,
    "BAM": 1.999479,
    "BBD": 2,
    "BDT": 101.678284,
    "BGN": 1.994309,
    "BHD": 0.377287,
    "BIF": 2050.5,
    "BMD": 1,
    "BND": 1.435107,
    "BOB": 6.908002,
    "BRL": 5.1768,
    "BSD": 1,
    "BTC": 0.000051273173,
    "BTN": 81.780255,
    "BWP": 13.329415,
    "BYN": 2.535832,
    "BZD": 2.01509,
    "CAD": 1.362837,
    "CDF": 2053.895408,
    "CHF": 0.993226,
    "CLF": 0.034083,
    "CLP": 940.46,
    "CNH": 7.100219,
    "CNY": 7.116,
    "COP": 4587.403251,
    "CRC": 625.38213,
    "CUC": 1,
    "CUP": 25.75,
    "CVE": 113,
    "CZK": 24.980116,
    "DJF": 177.827972,
    "DKK": 7.566413,
    "DOP": 53.55,
    "DZD": 140.48614,
    "EGP": 19.6161,
    "ERN": 15,
    "ETB": 52.6,
    "EUR": 1.017435,
    "FJD": 2.2884,
    "FKP": 0.883167,
    "GBP": 0.883167,
    "GEL": 2.825,
    "GGP": 0.883167,
    "GHS": 10.45,
    "GIP": 0.883167,
    "GMD": 55.4,
    "GNF": 8755,
    "GTQ": 7.88779,
    "GYD": 209.1581,
    "HKD": 7.849892,
    "HNL": 24.76,
    "HRK": 7.6591,
    "HTG": 120.465777,
    "HUF": 425.84989,
    "IDR": 15264.676977,
    "ILS": 3.55074,
    "IMP": 0.883167,
    "INR": 81.518156,
    "IQD": 1460,
    "IRR": 42350,
    "ISK": 144.39,
    "JEP": 0.883167,
    "JMD": 151.975891,
    "JOD": 0.7098,
    "JPY": 144.6727,
    "KES": 120.85,
    "KGS": 80.1763,
    "KHR": 4130,
    "KMF": 501.449796,
    "KPW": 900,
    "KRW": 1433.20015,
    "KWD": 0.3097,
    "KYD": 0.833069,
    "KZT": 475.505243,
    "LAK": 16525,
    "LBP": 1520,
    "LKR": 359.878545,
    "LRD": 153.799979,
    "LSL": 18.043407,
    "LYD": 5.055,
    "MAD": 10.953,
    "MDL": 19.449658,
    "MGA": 4197,
    "MKD": 62.846476,
    "MMK": 2099.244752,
    "MNT": 3271.946028,
    "MOP": 8.081999,
    "MRU": 37.869309,
    "MUR": 44.547422,
    "MVR": 15.45,
    "MWK": 1026,
    "MXN": 20.030502,
    "MYR": 4.648,
    "MZN": 63.900001,
    "NAD": 18.08,
    "NGN": 432.35,
    "NIO": 36,
    "NOK": 10.648194,
    "NPR": 130.846775,
    "NZD": 1.748907,
    "OMR": 0.385046,
    "PAB": 1,
    "PEN": 3.9815,
    "PGK": 3.52,
    "PHP": 58.900005,
    "PKR": 228.1,
    "PLN": 4.913021,
    "PYG": 7082.5759,
    "QAR": 3.639961,
    "RON": 5.0353,
    "RSD": 119.382252,
    "RUB": 58.025004,
    "RWF": 1041.5,
    "SAR": 3.75904,
    "SBD": 8.150095,
    "SCR": 13.197861,
    "SDG": 578.5,
    "SEK": 11.011312,
    "SGD": 1.430616,
    "SHP": 0.883167,
    "SLL": 13900,
    "SOS": 568.295392,
    "SRD": 28.713,
    "SSP": 130.26,
    "STD": 22750.290504,
    "STN": 25.35,
    "SVC": 8.747879,
    "SYP": 2512.53,
    "SZL": 18.08,
    "THB": 37.8049,
    "TJS": 9.847063,
    "TMT": 3.51,
    "TND": 3.253,
    "TOP": 2.440741,
    "TRY": 18.544125,
    "TTD": 6.785426,
    "TWD": 31.795498,
    "TZS": 2331.334461,
    "UAH": 36.740201,
    "UGX": 3838.89168,
    "USD": 1,
    "UYU": 41.698612,
    "UZS": 11015,
    "VES": 8.17345,
    "VND": 23889.159777,
    "VUV": 120.819439,
    "WST": 2.763664,
    "XAF": 667.393655,
    "XAG": 0.04909191,
    "XAU": 0.00058806,
    "XCD": 2.7017,
    "XDR": 0.780939,
    "XOF": 667.393655,
    "XPD": 0.00044953,
    "XPF": 121.412299,
    "XPT": 0.00110501,
    "YER": 250.249937,
    "ZAR": 17.842569,
    "ZMW": 15.720478,
    "ZWL": 322
  }
}