{
  "disclaimer": "Usage subject to terms: https://openexchangerates.org/terms",
  "license": "https://openexchangerates.org/license",
  "timestamp": 1666688400,
  "base": "USD",
  "rates": {
    "AED": 3.67298,
    "AFN": 86.590894,
    "ALL": 118.518642,
    "AMD": 401.402571,
    "ANG": 1.793363,
    "AOA": 455.41005,
    "ARS": 154.656905,
    "AUD": 1.582203,
    "AWG": 1.802,
    "AZN": 1.7,
    "BAM": 1.976854,
    "BBD": 2,
    "BDT": 100.978595,
    "BGN": 1.981528,
    "BHD": 0.37688,
    "BIF": 2054.708744,
    "BMD": 1,
    "BND": 1.415569,
    "BOB": 6.86036,
    "BRL": 5.3062,
    "BSD": 1,
    "BTC": 0.000051802718,
    "BTN": 82.15312,
    "BWP": 13.410255,
    "BYN": 2.517827,
    "BZD": 2.001162,
    "CAD": 1.37195,
    "CDF": 2034.201248,
    "CHF": 1.002841,
    "CLF": 0.035752,
    "CLP": 986.75,
    "CNH": 7.359465,
    "CNY": 7.3089,
    "COP": 4900.082739,
    "CRC": 617.089789,
    "CUC": 1,
    "CUP": 25.75,
    "CVE": 112.15,
    "CZK": 24.840888,
    "DJF": 177.228592,
    "DKK": 7.54618,
    "DOP": 53.538446,
    "DZD": 140.168403,
    "EGP": 19.6774,
    "ERN": 15,
    "ETB": 52.732986,
    "EUR": 1.014479,
    "FJD": 2.31065,
    "FKP": 0.883382,
    "GBP": 0.883382,
    "GEL": 2.76,
    "GGP": 0.883382,
    "GHS": 13.899802,
    "GIP": 0.883382,
    "GMD": 58,
    "GNF": 8650.993122,
    "GTQ": 7.783758,
    "GYD": 207.713144,
    "HKD": 7.84975,
    "HNL": 24.743286,
    "HRK": 7.6418,
    "HTG": 127.860167,
    "HUF": 418.567065,
    "IDR": 15621.244803,
    "ILS": 3.552727,
    "IMP": 0.883382,
    "INR": 82.75606,
    "IQD": 1449.027178,
    "IRR": 42300,
    "ISK": 144.54,
    "JEP": 0.883382,
    "JMD": 152.050574,
    "JOD": 0.709,
    "JPY": 148.86916667,
    "KES": 121.25,
    "KGS": 82.622098,
    "KHR": 4130.219661,
    "KMF": 498.850279,
    "KPW": 900,
    "KRW": 1437.447244,
    "KWD": 0.3103,
    "KYD": 0.827298,
    "KZT": 469.857049,
    "LAK": 17183.04321,
    "LBP": 1501.332717,
    "LKR": 364.364774,
    "LRD": 153.549955,
    "LSL": 18.211892,
    "LYD": 5.009874,
    "MAD": 10.891734,
    "MDL": 19.400604,
    "MGA": 4249.495764,
    "MKD": 62.277313,
    "MMK": 2089.818981,
    "MNT": 3368.982581,
    "MOP": 8.027088,
    "MRU": 37.688191,
    "MUR": 43.799997,
    "MVR": 15.395,
    "MWK": 1022.262518,
    "MXN": 19.900087,
    "MYR": 4.7348,
    "MZN": 63.899991,
    "NAD": 18.43,
    "NGN": 437.579273,
    "NIO": 35.949057,
    "NOK": 10.534945,
    "NPR": 131.731514,
    "NZD": 1.75654,
    "OMR": 0.385073,
    "PAB": 1,
    "PEN": 3.959469,
    "PGK": 3.498269,
    "PHP": 58.796501,
    "PKR": 218.714589,
    "PLN": 4.849287,
    "PYG": 7186.562862,
    "QAR": 3.615588,
    "RON": 4.97425,
    "RSD": 118.968579,
    "RUB": 61.764999,
    "RWF": 1055.660683,
    "SAR": 3.75991,
    "SBD": 8.180267,
    "SCR": 13.386953,
    "SDG": 570,
    "SEK": 11.141813,
    "SGD": 1.424443,
    "SHP": 0.883382,
    "SLL": 16960,
    "SOS": 566.834066,
    "SRD": 28.5235,
    "SSP": 130.26,
    "STD": 22900.590504,
    "STN": 25.1,
    "SVC": 8.68638,
    "SYP": 2512.53,
    "SZL": 18.253135,
    "THB": 38.2695,
    "TJS": 9.98772,
    "TMT": 3.51,
    "TND": 3.24,
    "TOP": 2.434817,
    "TRY": 18.60786,
    "TTD": 6.733511,
    "TWD": 32.352833,
    "TZS": 2332,
    "UAH": 36.752426,
    "UGX": 3787.682467,
    "USD": 1,
    "UYU": 41.217714,
    "UZS": 11044.974208,
    "VES": 8.3976,
    "VND": 24835.465427,
    "VUV": 124.473446,
    "WST": 2.815224,
    "XAF": 665.45453,
    "XAG": 0.05274275,
    "XAU": 0.00060835,
    "XCD": 2.70255,
    "XDR": 0.711778,
    "XOF": 665.45453,
    "XPD": 0.00050781,
    "XPF": 121.059534,
    "XPT": 0.00108936,
    "YER": 250.249937,
    "ZAR": 18.445094,
    "ZMW": 15.901857,
    "ZWL": 322
  }
}