{
  "disclaimer": "Usage subject to terms: https://openexchangerates.org/terms",
  "license": "https://openexchangerates.org/license",
  "timestamp": 1671469201,
  "base": "USD",
  "rates": {
    "AED": 3.673,
    "AFN": 87.499995,
    "ALL": 107.848224,
    "AMD": 395.132514,
    "ANG": 1.807185,
    "AOA": 504.2964,
    "ARS": 173.6428,
    "AUD": 1.490313,
    "AWG": 1.8025,
    "AZN": 1.7,
    "BAM": 1.8442,
    "BBD": 2,
    "BDT": 104.588158,
    "BGN": 1.8406,
    "BHD": 0.376982,
    "BIF": 2061,
    "BMD": 1,
    "BND": 1.357152,
    "BOB": 6.910536,
    "BRL": 5.3114,
    "BSD": 1,
    "BTC": 0.000060120614,
    "BTN": 82.627936,
    "BWP": 12.904181,
    "BYN": 2.524776,
    "BZD": 2.021023,
    "CAD": 1.363857,
    "CDF": 2031,
    "CHF": 0.930422,
    "CLF": 0.032177,
    "CLP": 887.85,
    "CNH": 6.984772,
    "CNY": 6.9795,
    "COP": 4776.66,
    "CRC": 596.266335,
    "CUC": 1,
    "CUP": 25.75,
    "CVE": 104.5,
    "CZK": 22.815133,
    "DJF": 177.735,
    "DKK": 7.002603,
    "DOP": 55.25,
    "DZD": 137.549558,
    "EGP": 24.739735,
    "ERN": 15,
    "ETB": 53.672821,
    "EUR": 0.941337,
    "FJD": 2.20515,
    "FKP": 0.821082,
    "GBP": 0.821082,
    "GEL": 2.65,
    "GGP": 0.821082,
    "GHS": 9,
    "GIP": 0.821082,
    "GMD": 61.9,
    "GNF": 8776,
    "GTQ": 7.891685,
    "GYD": 209.796434,
    "HKD": 7.778555,
    "HNL": 24.751084,
    "HRK": 7.0989,
    "HTG": 145.900907,
    "HUF": 378.924,
    "IDR": 15562.4,
    "ILS": 3.45747,
    "IMP": 0.821082,
    "INR": 82.661095,
    "IQD": 1459.644747,
    "IRR": 41400,
    "ISK": 142.59,
    "JEP": 0.821082,
    "JMD": 153.317676,
    "JOD": 0.7093,
    "JPY": 136.88366667,
    "KES": 123.1,
    "KGS": 84.95,
    "KHR": 4113.75,
    "KMF": 464.299621,
    "KPW": 900,
    "KRW": 1301.81174,
    "KWD": 0.306488,
    "KYD": 0.833349,
    "KZT": 467.566976,
    "LAK": 17326.494467,
    "LBP": 1512.339603,
    "LKR": 365.02785,
    "LRD": 154,
    "LSL": 17.636106,
    "LYD": 4.83,
    "MAD": 10.513954,
    "MDL": 19.325618,
    "MGA": 4440.817821,
    "MKD": 58.09749,
    "MMK": 2100.160567,
    "MNT": 3406.965265,
    "MOP": 8.01288,
    "MRU": 37.593468,
    "MUR": 43.899685,
    "MVR": 15.4,
    "MWK": 1027.198004,
    "MXN": 19.72919,
    "MYR": 4.4255,
    "MZN": 63.899991,
    "NAD": 17.68,
    "NGN": 445.96,
    "NIO": 36.610063,
    "NOK": 9.891478,
    "NPR": 132.203395,
    "NZD": 1.56976,
    "OMR": 0.384981,
    "PAB": 1,
    "PEN": 3.83,
    "PGK": 3.524409,
    "PHP": 55.400499,
    "PKR": 225.025,
    "PLN": 4.414428,
    "PYG": 7233.809628,
    "QAR": 3.64125,
    "RON": 4.6199,
    "RSD": 110.42964,
    "RUB": 68.374994,
    "RWF": 1066,
    "SAR": 3.761679,
    "SBD": 8.203583,
    "SCR": 12.928295,
    "SDG": 569,
    "SEK": 10.375247,
    "SGD": 1.355125,
    "SHP": 0.821082,
    "SLL": 17665,
    "SOS": 570.054682,
    "SRD": 31.695,
    "SSP": 130.26,
    "STD": 22823.990504,
    "STN": 23.101657,
    "SVC": 8.773038,
    "SYP": 2512.53,
    "SZL": 17.639072,
    "THB": 34.8475,
    "TJS": 10.200843,
    "TMT": 3.510001,
    "TND": 3.15625,
    "TOP": 2.345638,
    "TRY": 18.649329,
    "TTD": 6.805751,
    "TWD": 30.767499,
    "TZS": 2332,
    "UAH": 36.853005,
    "UGX": 3670.086443,
    "USD": 1,
    "UYU": 38.826248,
    "UZS": 11286.959181,
    "VES": 15.55225,
    "VND": 23699.74939,
    "VUV": 118.044,
    "WST": 2.69755,
    "XAF": 617.476319,
    "XAG": 0.04346097,
    "XAU": 0.00055932,
    "XCD": 2.70255,
    "XDR": 0.751888,
    "XOF": 617.476319,
    "XPD": 0.00059322,
    "XPF": 112.331334,
    "XPT": 0.0010119,
    "YER": 250.299955,
    "ZAR": 17.301043,
    "ZMW": 17.736318,
    "ZWL": 322
  }
}