{
  "disclaimer": "Usage subject to terms: https://openexchangerates.org/terms",
  "license": "https://openexchangerates.org/license",
  "timestamp": 1662735600,
  "base": "USD",
  "rates": {
    "AED": 3.6731,
    "AFN": 88.999995,
    "ALL": 116.713046,
    "AMD": 407.207836,
    "ANG": 1.804036,
    "AOA": 429.46635,
    "ARS": 141.375634,
    "AUD": 1.461949,
    "AWG": 1.8025,
    "AZN": 1.7,
    "BAM": 1.943392,
    "BBD": 2,
    "BDT": 95.11517,
    "BGN": 1.946519,
    "BHD": 0.376958,
    "BIF": 2048,
    "BMD": 1,
    "BND": 1.398734,
    "BOB": 6.916764,
    "BRL": 5.1486,
    "BSD": 1,
    "BTC": 0.000047466495,
    "BTN": 79.525354,
    "BWP": 12.932602,
    "BYN": 2.526629,
    "BZD": 2.017667,
    "CAD": 1.304589,
    "CDF": 2034,
    "CHF": 0.961483,
    "CLF": 0.031784,
    "CLP": 877.7,
    "CNH": 6.934555,
    "CNY": 6.9262,
    "COP": 4411.289314,
    "CRC": 651.622953,
    "CUC": 1,
    "CUP": 25.75,
    "CVE": 111.6,
    "CZK": 24.448032,
    "DJF": 179.5,
    "DKK": 7.405196,
    "DOP": 53,
    "DZD": 140.948,
    "EGP": 19.3146,
    "ERN": 15,
    "ETB": 52.851119,
    "EUR": 0.995847,
    "FJD": 2.2208,
    "FKP": 0.863345,
    "GBP": 0.863345,
    "GEL": 2.845,
    "GGP": 0.863345,
    "GHS": 10,
    "GIP": 0.863345,
    "GMD": 54.6,
    "GNF": 8750,
    "GTQ": 7.792649,
    "GYD": 209.417664,
    "HKD": 7.84895,
    "HNL": 24.676821,
    "HRK": 7.4934,
    "HTG": 119.617252,
    "HUF": 395.04695,
    "IDR": 14829.15,
    "ILS": 3.409112,
    "IMP": 0.863345,
    "INR": 79.601492,
    "IQD": 1460,
    "IRR": 42300,
    "ISK": 140.12,
    "JEP": 0.863345,
    "JMD": 151.849648,
    "JOD": 0.7099,
    "JPY": 142.43433333,
    "KES": 120.35,
    "KGS": 81.562202,
    "KHR": 4116,
    "KMF": 492.449964,
    "KPW": 900,
    "KRW": 1378.063028,
    "KWD": 0.308422,
    "KYD": 0.834153,
    "KZT": 474.225204,
    "LAK": 15755,
    "LBP": 1517,
    "LKR": 360.354326,
    "LRD": 153.899977,
    "LSL": 17.27,
    "LYD": 4.945,
    "MAD": 10.5975,
    "MDL": 19.381803,
    "MGA": 4209.10726,
    "MKD": 61.627935,
    "MMK": 2102.085142,
    "MNT": 3203.980782,
    "MOP": 8.092229,
    "MRU": 37.66,
    "MUR": 44.948297,
    "MVR": 15.4,
    "MWK": 1024.5,
    "MXN": 19.887393,
    "MYR": 4.498,
    "MZN": 63.899991,
    "NAD": 17.27,
    "NGN": 427.26,
    "NIO": 35.975398,
    "NOK": 9.922027,
    "NPR": 127.083865,
    "NZD": 1.637444,
    "OMR": 0.384979,
    "PAB": 1,
    "PEN": 3.887978,
    "PGK": 3.527056,
    "PHP": 56.777995,
    "PKR": 228.474617,
    "PLN": 4.688348,
    "PYG": 6933.632235,
    "QAR": 3.641,
    "RON": 4.878399,
    "RSD": 116.857457,
    "RUB": 60.600604,
    "RWF": 1036.059309,
    "SAR": 3.757247,
    "SBD": 8.200194,
    "SCR": 13.123762,
    "SDG": 577.5,
    "SEK": 10.613292,
    "SGD": 1.399336,
    "SHP": 0.863345,
    "SLL": 13748.9,
    "SOS": 569.052833,
    "SRD": 26.4805,
    "SSP": 130.26,
    "STD": 22392.090504,
    "STN": 24.75,
    "SVC": 8.758856,
    "SYP": 2512.53,
    "SZL": 17.271987,
    "THB": 36.4,
    "TJS": 10.089244,
    "TMT": 3.5,
    "TND": 3.2015,
    "TOP": 2.372378,
    "TRY": 18.2373,
    "TTD": 6.800708,
    "TWD": 30.825046,
    "TZS": 2334.289191,
    "UAH": 36.968898,
    "UGX": 3818.711666,
    "USD": 1,
    "UYU": 40.78914,
    "UZS": 10988.563875,
    "VES": 7.922895,
    "VND": 23523.881942,
    "VUV": 117.93204,
    "WST": 2.68729,
    "XAF": 653.232521,
    "XAG": 0.05339042,
    "XAU": 0.00058319,
    "XCD": 2.70255,
    "XDR": 0.741663,
    "XOF": 653.232521,
    "XPD": 0.00046083,
    "XPF": 118.836105,
    "XPT": 0.00113236,
    "YER": 250.249937,
    "ZAR": 17.27571,
    "ZMW": 15.515247,
    "ZWL": 322
  }
}