{
  "disclaimer": "Usage subject to terms: https://openexchangerates.org/terms",
  "license": "https://openexchangerates.org/license",
  "timestamp": 1661497207,
  "base": "USD",
  "rates": {
    "AED": 3.673,
    "AFN": 88.529411,
    "ALL": 117.150625,
    "AMD": 404.403591,
    "ANG": 1.805009,
    "AOA": 429.2118,
    "ARS": 137.39,
    "AUD": 1.437412,
    "AWG": 1.805,
    "AZN": 1.7,
    "BAM": 1.96269,
    "BBD": 2,
    "BDT": 95.170434,
    "BGN": 1.962765,
    "BHD": 0.376951,
    "BIF": 2065.476537,
    "BMD": 1,
    "BND": 1.392166,
    "BOB": 6.920414,
    "BRL": 5.1102,
    "BSD": 1,
    "BTC": 0.000046649255,
    "BTN": 79.958553,
    "BWP": 12.774848,
    "BYN": 2.527923,
    "BZD": 2.018745,
    "CAD": 1.295441,
    "CDF": 2056.163768,
    "CHF": 0.964211,
    "CLF": 0.032563,
    "CLP": 898.5,
    "CNH": 6.866278,
    "CNY": 6.8604,
    "COP": 4419.287604,
    "CRC": 635.741669,
    "CUC": 1,
    "CUP": 25.75,
    "CVE": 110.8,
    "CZK": 24.7546,
    "DJF": 178.294921,
    "DKK": 7.466141,
    "DOP": 53.236057,
    "DZD": 141.120174,
    "EGP": 19.1927,
    "ERN": 15,
    "ETB": 52.83145,
    "EUR": 1.003761,
    "FJD": 2.20415,
    "FKP": 0.847197,
    "GBP": 0.847197,
    "GEL": 2.845,
    "GGP": 0.847197,
    "GHS": 9.939992,
    "GIP": 0.847197,
    "GMD": 54.3,
    "GNF": 8641.100361,
    "GTQ": 7.74919,
    "GYD": 209.52708,
    "HKD": 7.845715,
    "HNL": 24.639113,
    "HRK": 7.5409,
    "HTG": 126.693808,
    "HUF": 413.745753,
    "IDR": 14811.586723,
    "ILS": 3.270022,
    "IMP": 0.847197,
    "INR": 79.905494,
    "IQD": 1461.721583,
    "IRR": 42300,
    "ISK": 140.64,
    "JEP": 0.847197,
    "JMD": 151.156277,
    "JOD": 0.709,
    "JPY": 136.86151786,
    "KES": 119.9,
    "KGS": 80.680463,
    "KHR": 4110.294768,
    "KMF": 494.149841,
    "KPW": 900,
    "KRW": 1332.518399,
    "KWD": 0.307835,
    "KYD": 0.834613,
    "KZT": 466.959856,
    "LAK": 15304.14545,
    "LBP": 1514.287396,
    "LKR": 365.567647,
    "LRD": 153.650045,
    "LSL": 16.863152,
    "LYD": 4.938209,
    "MAD": 10.569376,
    "MDL": 19.38957,
    "MGA": 4213.438596,
    "MKD": 61.830789,
    "MMK": 2103.235931,
    "MNT": 3193.450782,
    "MOP": 8.094349,
    "MRU": 37.737894,
    "MUR": 44.800001,
    "MVR": 15.36,
    "MWK": 1030.725497,
    "MXN": 19.9624,
    "MYR": 4.474,
    "MZN": 63.899991,
    "NAD": 16.97,
    "NGN": 426.39867,
    "NIO": 35.994801,
    "NOK": 9.686454,
    "NPR": 127.935144,
    "NZD": 1.613241,
    "OMR": 0.384982,
    "PAB": 1,
    "PEN": 3.875244,
    "PGK": 3.529636,
    "PHP": 56.027497,
    "PKR": 219.838108,
    "PLN": 4.756234,
    "PYG": 6868.702495,
    "QAR": 3.641,
    "RON": 4.8895,
    "RSD": 117.786015,
    "RUB": 60.075,
    "RWF": 1033.121589,
    "SAR": 3.756799,
    "SBD": 8.223773,
    "SCR": 13.15948,
    "SDG": 570,
    "SEK": 10.61257,
    "SGD": 1.391785,
    "SHP": 0.847197,
    "SLL": 13748.9,
    "SOS": 569.389448,
    "SRD": 24.6205,
    "SSP": 130.26,
    "STD": 22392.090504,
    "STN": 24.75,
    "SVC": 8.763585,
    "SYP": 2512.53,
    "SZL": 16.863407,
    "THB": 35.915479,
    "TJS": 10.19538,
    "TMT": 3.51,
    "TND": 3.1955,
    "TOP": 2.343463,
    "TRY": 18.1773,
    "TTD": 6.801337,
    "TWD": 30.193,
    "TZS": 2332,
    "UAH": 36.990182,
    "UGX": 3797.685995,
    "USD": 1,
    "UYU": 40.418345,
    "UZS": 10932.183032,
    "VES": 6.274,
    "VND": 23421.946685,
    "VUV": 117.30904,
    "WST": 2.692725,
    "XAF": 658.424373,
    "XAG": 0.05197518,
    "XAU": 0.00056987,
    "XCD": 2.70255,
    "XDR": 0.740433,
    "XOF": 658.424373,
    "XPD": 0.000466,
    "XPF": 119.780607,
    "XPT": 0.00112931,
    "YER": 250.250057,
    "ZAR": 16.78754,
    "ZMW": 16.169632,
    "ZWL": 322
  }
}