{
  "disclaimer": "Usage subject to terms: https://openexchangerates.org/terms",
  "license": "https://openexchangerates.org/license",
  "timestamp": 1674576000,
  "base": "USD",
  "rates": {
    "AED": 3.673,
    "AFN": 89.499995,
    "ALL": 106.881886,
    "AMD": 396.4,
    "ANG": 1.802386,
    "AOA": 503.173,
    "ARS": 184.6942,
    "AUD": 1.418428,
    "AWG": 1.8,
    "AZN": 1.7,
    "BAM": 1.799871,
    "BBD": 2,
    "BDT": 106.604906,
    "BGN": 1.7985,
    "BHD": 0.377008,
    "BIF": 2062.5,
    "BMD": 1,
    "BND": 1.319597,
    "BOB": 6.910327,
    "BRL": 5.159,
    "BSD": 1,
    "BTC": 0.00004360674,
    "BTN": 81.663514,
    "BWP": 12.804811,
    "BYN": 2.52418,
    "BZD": 2.015736,
    "CAD": 1.336237,
    "CDF": 2040,
    "CHF": 0.923124,
    "CLF": 0.028999,
    "CLP": 800.1,
    "CNH": 6.78521,
    "CNY": 6.7845,
    "COP": 4552.38,
    "CRC": 563.32465,
    "CUC": 1,
    "CUP": 25.75,
    "CVE": 101.475232,
    "CZK": 21.944975,
    "DJF": 178.029113,
    "DKK": 6.839984,
    "DOP": 56.696268,
    "DZD": 135.770692,
    "EGP": 29.8481,
    "ERN": 15,
    "ETB": 53.64487,
    "EUR": 0.919463,
    "FJD": 2.15665,
    "FKP": 0.811986,
    "GBP": 0.811986,
    "GEL": 2.645,
    "GGP": 0.811986,
    "GHS": 12.400221,
    "GIP": 0.811986,
    "GMD": 62.475,
    "GNF": 8612.900243,
    "GTQ": 7.850435,
    "GYD": 209.214955,
    "HKD": 7.830755,
    "HNL": 24.670316,
    "HRK": 6.929658,
    "HTG": 149.002898,
    "HUF": 359.487062,
    "IDR": 14943.68289,
    "ILS": 3.363853,
    "IMP": 0.811986,
    "INR": 81.5522,
    "IQD": 1459.559448,
    "IRR": 41900,
    "ISK": 143.93,
    "JEP": 0.811986,
    "JMD": 154.172535,
    "JOD": 0.7099,
    "JPY": 130.08955,
    "KES": 124.31,
    "KGS": 86.05,
    "KHR": 4115.156542,
    "KMF": 453.550077,
    "KPW": 900,
    "KRW": 1234.590705,
    "KWD": 0.305394,
    "KYD": 0.833322,
    "KZT": 461.679125,
    "LAK": 16839.673093,
    "LBP": 1512.303789,
    "LKR": 364.016853,
    "LRD": 156.499964,
    "LSL": 17.269594,
    "LYD": 4.758241,
    "MAD": 10.145221,
    "MDL": 18.841351,
    "MGA": 4267.705914,
    "MKD": 56.625451,
    "MMK": 2100.102905,
    "MNT": 3406.965265,
    "MOP": 8.063905,
    "MRU": 36.390743,
    "MUR": 44.303041,
    "MVR": 15.37,
    "MWK": 1026.481397,
    "MXN": 18.83665,
    "MYR": 4.2845,
    "MZN": 63.900001,
    "NAD": 17.22,
    "NGN": 455.07,
    "NIO": 36.541921,
    "NOK": 9.866154,
    "NPR": 130.662043,
    "NZD": 1.537699,
    "OMR": 0.385008,
    "PAB": 1,
    "PEN": 3.874877,
    "PGK": 3.524415,
    "PHP": 54.781501,
    "PKR": 231.510658,
    "PLN": 4.337313,
    "PYG": 7437.665231,
    "QAR": 3.654176,
    "RON": 4.5192,
    "RSD": 107.911136,
    "RUB": 69.013112,
    "RWF": 1077.589061,
    "SAR": 3.7546,
    "SBD": 8.247738,
    "SCR": 13.293671,
    "SDG": 576.5,
    "SEK": 10.217548,
    "SGD": 1.320165,
    "SHP": 0.811986,
    "SLL": 17665,
    "SOS": 568.554729,
    "SRD": 32.2865,
    "SSP": 130.26,
    "STD": 22823.990504,
    "STN": 22.546358,
    "SVC": 8.750109,
    "SYP": 2512.53,
    "SZL": 17.269686,
    "THB": 32.7899,
    "TJS": 10.255471,
    "TMT": 3.51,
    "TND": 3.095,
    "TOP": 2.320065,
    "TRY": 18.8058,
    "TTD": 6.789126,
    "TWD": 30.3083,
    "TZS": 2339,
    "UAH": 36.918888,
    "UGX": 3675.051649,
    "USD": 1,
    "UYU": 39.18363,
    "UZS": 11270.8806,
    "VES": 21.488482,
    "VND": 23449.410804,
    "VUV": 118.044,
    "WST": 2.69755,
    "XAF": 603.128336,
    "XAG": 0.04232536,
    "XAU": 0.00051678,
    "XCD": 2.70255,
    "XDR": 0.740645,
    "XOF": 603.128336,
    "XPD": 0.00057276,
    "XPF": 109.721148,
    "XPT": 0.0009445,
    "YER": 250.374935,
    "ZAR": 17.20873,
    "ZMW": 18.76538,
    "ZWL": 322
  }
}