{
  "disclaimer": "Usage subject to terms: https://openexchangerates.org/terms",
  "license": "https://openexchangerates.org/license",
  "timestamp": 1675443600,
  "base": "USD",
  "rates": {
    "AED": 3.67295,
    "AFN": 90.5,
    "ALL": 106.297024,
    "AMD": 396.48,
    "ANG": 1.802145,
    "AOA": 504.2749,
    "ARS": 187.942625,
    "AUD": 1.439873,
    "AWG": 1.8025,
    "AZN": 1.7,
    "BAM": 1.789455,
    "BBD": 2,
    "BDT": 107.348067,
    "BGN": 1.8015,
    "BHD": 0.376954,
    "BIF": 2071,
    "BMD": 1,
    "BND": 1.310593,
    "BOB": 6.909894,
    "BRL": 5.1341,
    "BSD": 1,
    "BTC": 0.000042456472,
    "BTN": 81.826993,
    "BWP": 12.73826,
    "BYN": 2.524486,
    "BZD": 2.0156,
    "CAD": 1.339533,
    "CDF": 2045,
    "CHF": 0.925028,
    "CLF": 0.028862,
    "CLP": 795.45,
    "CNH": 6.795093,
    "CNY": 6.7752,
    "COP": 4649.2,
    "CRC": 560.369504,
    "CUC": 1,
    "CUP": 25.75,
    "CVE": 100.885183,
    "CZK": 21.955597,
    "DJF": 178.018683,
    "DKK": 6.877776,
    "DOP": 56.627098,
    "DZD": 135.527162,
    "EGP": 30.2763,
    "ERN": 15,
    "ETB": 53.681009,
    "EUR": 0.923772,
    "FJD": 2.174,
    "FKP": 0.828369,
    "GBP": 0.828369,
    "GEL": 2.63,
    "GGP": 0.828369,
    "GHS": 12.249411,
    "GIP": 0.828369,
    "GMD": 61,
    "GNF": 8608.73722,
    "GTQ": 7.849585,
    "GYD": 210.992906,
    "HKD": 7.846206,
    "HNL": 24.651983,
    "HRK": 6.954246,
    "HTG": 149.958604,
    "HUF": 358.191924,
    "IDR": 15050.990844,
    "ILS": 3.41815,
    "IMP": 0.828369,
    "INR": 82.273045,
    "IQD": 1459.475968,
    "IRR": 42200,
    "ISK": 141.82,
    "JEP": 0.828369,
    "JMD": 154.497001,
    "JOD": 0.71,
    "JPY": 131.07979184,
    "KES": 124.75,
    "KGS": 86.2206,
    "KHR": 4109.959142,
    "KMF": 451.300322,
    "KPW": 900,
    "KRW": 1244.902753,
    "KWD": 0.305063,
    "KYD": 0.833349,
    "KZT": 458.025095,
    "LAK": 16840.853566,
    "LBP": 1508.635672,
    "LKR": 364.993171,
    "LRD": 156.949975,
    "LSL": 17.146596,
    "LYD": 4.731032,
    "MAD": 10.162172,
    "MDL": 18.73545,
    "MGA": 4270.509405,
    "MKD": 56.373659,
    "MMK": 2099.957136,
    "MNT": 3406.965265,
    "MOP": 8.080773,
    "MRU": 36.373202,
    "MUR": 45.410001,
    "MVR": 15.3525,
    "MWK": 1026.353929,
    "MXN": 18.883527,
    "MYR": 4.26,
    "MZN": 63.899991,
    "NAD": 17.09,
    "NGN": 460.54,
    "NIO": 36.53789,
    "NOK": 10.190145,
    "NPR": 130.923012,
    "NZD": 1.576479,
    "OMR": 0.384979,
    "PAB": 1,
    "PEN": 3.822869,
    "PGK": 3.524256,
    "PHP": 54.046502,
    "PKR": 270.237866,
    "PLN": 4.351752,
    "PYG": 7307.885306,
    "QAR": 3.648508,
    "RON": 4.52551,
    "RSD": 108.388394,
    "RUB": 70.500002,
    "RWF": 1082.566894,
    "SAR": 3.752635,
    "SBD": 8.197272,
    "SCR": 13.967952,
    "SDG": 583.5,
    "SEK": 10.521174,
    "SGD": 1.321569,
    "SHP": 0.828369,
    "SLL": 17665,
    "SOS": 568.44773,
    "SRD": 32.284,
    "SSP": 130.26,
    "STD": 22823.990504,
    "STN": 22.415883,
    "SVC": 8.749514,
    "SYP": 2512.53,
    "SZL": 17.146138,
    "THB": 33.412635,
    "TJS": 10.314509,
    "TMT": 3.51,
    "TND": 3.0405,
    "TOP": 2.31195,
    "TRY": 18.820395,
    "TTD": 6.787106,
    "TWD": 29.9145,
    "TZS": 2339,
    "UAH": 36.932316,
    "UGX": 3683.784116,
    "USD": 1,
    "UYU": 38.579248,
    "UZS": 11316.318726,
    "VES": 22.652448,
    "VND": 23449.410804,
    "VUV": 118.044,
    "WST": 2.69755,
    "XAF": 605.954788,
    "XAG": 0.04465582,
    "XAU": 0.00053521,
    "XCD": 2.70255,
    "XDR": 0.736728,
    "XOF": 605.954788,
    "XPD": 0.00061781,
    "XPF": 110.235336,
    "XPT": 0.00101801,
    "YER": 250.399941,
    "ZAR": 17.480706,
    "ZMW": 19.104005,
    "ZWL": 322
  }
}