{
  "disclaimer": "Usage subject to terms: https://openexchangerates.org/terms",
  "license": "https://openexchangerates.org/license",
  "timestamp": 1702508400,
  "base": "USD",
  "rates": {
    "AED": 3.672307,
    "AFN": 69.566427,
    "ALL": 94.825628,
    "AMD": 403.600084,
    "ANG": 1.802383,
    "AOA": 831.261,
    "ARS": 793.522184,
    "AUD": 1.501852,
    "AWG": 1.8,
    "AZN": 1.7,
    "BAM": 1.813865,
    "BBD": 2,
    "BDT": 110.011591,
    "BGN": 1.801805,
    "BHD": 0.376939,
    "BIF": 2846.192695,
    "BMD": 1,
    "BND": 1.343615,
    "BOB": 6.91091,
    "BRL": 4.92,
    "BSD": 1,
    "BTC": 0.000023264335,
    "BTN": 83.418918,
    "BWP": 13.699532,
    "BYN": 3.294969,
    "BZD": 2.015886,
    "CAD": 1.351279,
    "CDF": 2735.65094,
    "CHF": 0.871236,
    "CLF": 0.031721,
    "CLP": 875.28,
    "CNH": 7.13735,
    "CNY": 7.1726,
    "COP": 3954.510109,
    "CRC": 527.128109,
    "CUC": 1,
    "CUP": 25.75,
    "CVE": 102.262952,
    "CZK": 22.474451,
    "DJF": 177.827972,
    "DKK": 6.855,
    "DOP": 56.913922,
    "DZD": 134.610857,
    "EGP": 30.8997,
    "ERN": 15,
    "ETB": 56.064997,
    "EUR": 0.919299,
    "FJD": 2.22275,
    "FKP": 0.792103,
    "GBP": 0.792103,
    "GEL": 2.68,
    "GGP": 0.792103,
    "GHS": 12.045869,
    "GIP": 0.792103,
    "GMD": 67.425,
    "GNF": 8598.724056,
    "GTQ": 7.828099,
    "GYD": 209.228418,
    "HKD": 7.811429,
    "HNL": 24.732807,
    "HRK": 6.925367,
    "HTG": 132.232768,
    "HUF": 348.395249,
    "IDR": 15434.779469,
    "ILS": 3.70075,
    "IMP": 0.792103,
    "INR": 83.270763,
    "IQD": 1310.109924,
    "IRR": 42275,
    "ISK": 139.496667,
    "JEP": 0.792103,
    "JMD": 155.690282,
    "JOD": 0.7094,
    "JPY": 142.574,
    "KES": 154.03023,
    "KGS": 89.2,
    "KHR": 4112.221474,
    "KMF": 456.625242,
    "KPW": 900,
    "KRW": 1293.0281,
    "KWD": 0.308048,
    "KYD": 0.833453,
    "KZT": 458.752538,
    "LAK": 20717.062816,
    "LBP": 15033.041641,
    "LKR": 326.529197,
    "LRD": 188.250075,
    "LSL": 19.093204,
    "LYD": 4.834255,
    "MAD": 10.186545,
    "MDL": 17.828824,
    "MGA": 4575,
    "MKD": 57.069426,
    "MMK": 2100.182506,
    "MNT": 3450,
    "MOP": 8.049467,
    "MRU": 39.55,
    "MUR": 44.649996,
    "MVR": 15.395,
    "MWK": 1683.690822,
    "MXN": 17.253351,
    "MYR": 4.7065,
    "MZN": 63.899991,
    "NAD": 19.09,
    "NGN": 796.040353,
    "NIO": 36.683367,
    "NOK": 10.74571,
    "NPR": 133.469947,
    "NZD": 1.619472,
    "OMR": 0.384972,
    "PAB": 1,
    "PEN": 3.779207,
    "PGK": 3.777912,
    "PHP": 55.862501,
    "PKR": 283.621216,
    "PLN": 3.956591,
    "PYG": 7338.449083,
    "QAR": 3.642482,
    "RON": 4.5677,
    "RSD": 107.727,
    "RUB": 89.95,
    "RWF": 1251.813303,
    "SAR": 3.750648,
    "SBD": 8.489576,
    "SCR": 13.357844,
    "SDG": 601,
    "SEK": 10.325885,
    "SGD": 1.333462,
    "SHP": 0.792103,
    "SLL": 20969.5,
    "SOS": 571.330088,
    "SRD": 37.4235,
    "SSP": 130.26,
    "STD": 22281.8,
    "STN": 22.831715,
    "SVC": 8.751217,
    "SYP": 2512.53,
    "SZL": 19.095124,
    "THB": 35.261779,
    "TJS": 10.920852,
    "TMT": 3.5,
    "TND": 3.121,
    "TOP": 2.36538,
    "TRY": 29.011615,
    "TTD": 6.792204,
    "TWD": 31.212,
    "TZS": 2505.088996,
    "UAH": 37.034922,
    "UGX": 3790.410478,
    "USD": 1,
    "UYU": 39.32511,
    "UZS": 12372.000281,
    "VES": 35.55416,
    "VND": 24280.685073,
    "VUV": 118.722,
    "WST": 2.8,
    "XAF": 603.020846,
    "XAG": 0.04200269,
    "XAU": 0.00049322,
    "XCD": 2.70255,
    "XDR": 0.752516,
    "XOF": 603.020846,
    "XPD": 0.00100662,
    "XPF": 109.701593,
    "XPT": 0.00106535,
    "YER": 250.324978,
    "ZAR": 18.6671,
    "ZMW": 24.476604,
    "ZWL": 322
  }
}